setup.py
sxb/__init__.py
sxb/utils.py
sxb.egg-info/PKG-INFO
sxb.egg-info/SOURCES.txt
sxb.egg-info/dependency_links.txt
sxb.egg-info/not-zip-safe
sxb.egg-info/top_level.txt