Metadata-Version: 1.0
Name: sxb
Version: 1.0.0
Summary: sxb stuff
Home-page: UNKNOWN
Author: UNKNOWN
Author-email: UNKNOWN
License: UNKNOWN
Platform: UNKNOWN
